<?xml version="1.0" encoding="UTF-8" standalone="yes"?>
<response>
 <header>
  <resultCode>
   00
  </resultCode>
  <resultMsg>
   NORMAL SERVICE.
  </resultMsg>
 </header>
 <body>
  <items>
   <item>
    <billId>
     PRC_X1X7B0L7H0X6I1K5R5Q8S2Z0D7N7O7
    </billId>
    <billName>
     외무공무원법 일부개정법률안(최경환의원 등 11인)
    </billName>
    <billNo>
     2007816
    </billNo>
    <passGubn>
     계류의안
    </passGubn>
    <procStageCd>
     소관위심사
    </procStageCd>
    <proposeDt>
     2017-07-06
    </proposeDt>
    <proposerKind>
     의원
    </proposerKind>
    <summary>제안이유 및 주요내용 2016년 외교부 국정감사에서는 2016년 10월 현재 127개 비영어권 재외공관 중 42개 재외공관 외무공무원들의 주재국 언어 활용능력이 현저히 떨어진다고 지적된 바 있음. 이는 현행 「외무공무원의 인사·복무·교육·훈련·소환에 관한 예규」에 따라 영어와 주재국 언어 중 어느 하나의 검정점수가 기준 점수 이상이 되면 임용이 가능하기에 대다수의 외무공무원들이 주재국 언어보다 능숙한 영어 검정점수를 인정받아 발령되고 있기 때문임. 이에 외교부장관이 주재국 언어를 사용하는 재외공관에 외무공무원을 임용할 경우 주재국 언어 활용능력 수준을 충분히 고려하도록 하고, 재외공관에 임용될 자를 대상으로 교육을 실시하되 주재국 언어 활용능력 강화를 위한 강좌를 포함하며, 또한 재외공관의 장은 주재국언어 활용능력 수준이 떨어지는 외무공무원에 대하여 학습을 실시하여 재외공관 근무 외무공무원의 주재국 언어 활용능력 역량을 강화시키려는 것임(안 제16조의2 신설).</summary>
   </item>
   <item>
    <billId>
     PRC_E1C6R1O2C0L7E1K8K2R8W2Z5K3C3K8
    </billId>
    <billName>
     원자력 진흥법 일부개정법률안(최경환의원 등 11인)
    </billName>
    <billNo>
     2004183
    </billNo>
    <passGubn>
     계류의안
    </passGubn>
    <procStageCd>
     소관위심사
    </procStageCd>
    <proposeDt>
     2016-12-07
    </proposeDt>
    <proposerKind>
     의원
    </proposerKind>
    <summary>■ 제안이유 및 주요내용 우리나라의 원자력발전소는 1970∼80년대에 집중적으로 건설되기 시작하여 2016년 6월말 현재 국내에 총 24기가 상업운전 중에 있으며, 2017년 6월 운영허가 만료 예정인 고리 1호기를 포함한 모든 원자력발전소가 향후 20∼30년 내 운영허가 만료 시점에 도달할 예정임. 또한, 향후 2050년까지 전 세계적으로 430여기의 원전이 해체될 것으로 전망되고 이에 따른 비용이 440조원에 이를 것으로 추산되고 있어, 원자력시설의 해체 관련 기술과 산업에 대한 세계 각국의 관심이 집중되고 있음. 현재 우리나라는 설비용량 면에서 세계 6위의 원자력 발전국으로 향후 원자력발전소의 자립적 해체와 해외시장 진출을 위한 경쟁력 제고를 위하여 기술적 준비가 요구되고 있는 데 반하여 원자력시설의 해체에 필요한 상용기술은 58개 중 41개만 확보한 상태로 대응역량 강화가 필요한 상황임. 이에 원자력시설 해체 및 해체기술에 관한 사항을 원자력진흥위원회의 심의·의결 사항, 미래창조과학부의 원자력진흥종합계획 수립 대상에 각각 추가함으로써 원자력발전소의 안전한 해체기술과 지속 가능한 미래성장 동력을 확보하려는 것임(안 제2조제5호, 제4조제8호, 제9조제2항제5호 신설).</summary>
   </item>
  </items>
  <numOfRows>
   1000
  </numOfRows>
  <pageNo>
   1
  </pageNo>
  <totalCount>
   2
  </totalCount>
 </body>
</response>