<?xml version="1.0" encoding="UTF-8" standalone="yes"?>
<response>
 <header>
  <resultCode>
   00
  </resultCode>
  <resultMsg>
   NORMAL SERVICE.
  </resultMsg>
 </header>
 <body>
  <items>
   <item>
    <billid>
     PRC_Q1G6E0I9X2V1A1V6D3M7D0S3H0G5O3
    </billid>
    <billname>
     주택임대차보호법 일부개정법률안
    </billname>
    <billno>
     2002378
    </billno>
    <committeename>
     법제사법위원회
    </committeename>
    <proposedt>
     2016-09-21
    </proposedt>
    <proposer>
     김현아의원 등 10인
    </proposer>
    <proposerkind>
     의원
    </proposerkind>
    <submitdt>
     2016-09-22
    </submitdt>
   </item>
   <item>
    <billid>
     PRC_Q1A6X0K9H2T1M1K6F2U2L1Y6Z0Q5J8
    </billid>
    <billname>
     독점규제 및 공정거래에 관한 법률 일부개정법률안
    </billname>
    <billno>
     2002375
    </billno>
    <committeename>
     정무위원회
    </committeename>
    <proposedt>
     2016-09-21
    </proposedt>
    <proposer>
     이언주의원 등 10인
    </proposer>
    <proposerkind>
     의원
    </proposerkind>
    <submitdt>
     2016-09-22
    </submitdt>
   </item>
   <item>
    <billid>
     PRC_V1T6J0Z9L2P1Q1H5I3Z8M4P2W4J1X5
    </billid>
    <billname>
     정보통신망 이용촉진 및 정보보호 등에 관한 법률 일부개정법률안
    </billname>
    <billno>
     2002374
    </billno>
    <committeename>
     과학기술정보방송통신위원회
    </committeename>
    <proposedt>
     2016-09-21
    </proposedt>
    <proposer>
     신용현의원 등 14인
    </proposer>
    <proposerkind>
     의원
    </proposerkind>
    <submitdt>
     2016-09-22
    </submitdt>
   </item>
   <item>
    <billid>
     PRC_K1S6H0D9T2S1W1G4M1F8O3P0V6E3A2
    </billid>
    <billname>
     월남전 참전군인의 전투근무수당미지급금 지급에 관한 특별법안
    </billname>
    <billno>
     2002372
    </billno>
    <committeename>
     국방위원회
    </committeename>
    <proposedt>
     2016-09-21
    </proposedt>
    <proposer>
     정동영의원 등 17인
    </proposer>
    <proposerkind>
     의원
    </proposerkind>
    <submitdt>
     2016-09-22
    </submitdt>
   </item>
   <item>
    <billid>
     PRC_A1B6D0G9S2E1B1Z1C4J8Q4Y3J0E5K5
    </billid>
    <billname>
     도로교통법 일부개정법률안
    </billname>
    <billno>
     2002365
    </billno>
    <committeename>
     행정안전위원회
    </committeename>
    <proposedt>
     2016-09-21
    </proposedt>
    <proposer>
     주승용의원 등 13인
    </proposer>
    <proposerkind>
     의원
    </proposerkind>
    <submitdt>
     2016-09-22
    </submitdt>
   </item>
   <item>
    <billid>
     PRC_Y1I6C0H9G2P1H1W1G4G6J1L0L5F5H8
    </billid>
    <billname>
     경찰관 직무집행법 일부개정법률안
    </billname>
    <billno>
     2002364
    </billno>
    <committeename>
     행정안전위원회
    </committeename>
    <proposedt>
     2016-09-21
    </proposedt>
    <proposer>
     주승용의원 등 15인
    </proposer>
    <proposerkind>
     의원
    </proposerkind>
    <submitdt>
     2016-09-22
    </submitdt>
   </item>
   <item>
    <billid>
     PRC_M1B6Y0B9E2B1W1E1T4A0X4A6B2G6O0
    </billid>
    <billname>
     산림자원의 조성 및 관리에 관한 법률 일부개정법률안
    </billname>
    <billno>
     2002361
    </billno>
    <committeename>
     농림축산식품해양수산위원회
    </committeename>
    <proposedt>
     2016-09-21
    </proposedt>
    <proposer>
     주승용의원 등 15인
    </proposer>
    <proposerkind>
     의원
    </proposerkind>
    <submitdt>
     2016-09-22
    </submitdt>
   </item>
   <item>
    <billid>
     PRC_M1M6X0F9I2I1W1C1G3O8Z1P9J3X6F0
    </billid>
    <billname>
     상법 일부개정법률안
    </billname>
    <billno>
     2002360
    </billno>
    <committeename>
     법제사법위원회
    </committeename>
    <proposedt>
     2016-09-21
    </proposedt>
    <proposer>
     주승용의원 등 10인
    </proposer>
    <proposerkind>
     의원
    </proposerkind>
    <submitdt>
     2016-09-22
    </submitdt>
   </item>
   <item>
    <billid>
     PRC_G1V6Q0C9A2Y1O1G1O2B6X3K6F3P4J7
    </billid>
    <billname>
     지방교육재정교부금법 일부개정법률안
    </billname>
    <billno>
     2002359
    </billno>
    <committeename>
     교육위원회
    </committeename>
    <proposedt>
     2016-09-21
    </proposedt>
    <proposer>
     김두관의원 등 10인
    </proposer>
    <proposerkind>
     의원
    </proposerkind>
    <submitdt>
     2016-09-22
    </submitdt>
   </item>
   <item>
    <billid>
     PRC_I1A6L0G9S2D1A0B9C3T2T0D0M9D1F3
    </billid>
    <billname>
     근로기준법 일부개정법률안
    </billname>
    <billno>
     2002357
    </billno>
    <committeename>
     환경노동위원회
    </committeename>
    <proposedt>
     2016-09-21
    </proposedt>
    <proposer>
     이정미의원 등 10인
    </proposer>
    <proposerkind>
     의원
    </proposerkind>
    <submitdt>
     2016-09-22
    </submitdt>
   </item>
   <item>
    <billid>
     PRC_J1J6F0O9H2Z0Z1Q8L0G8K1D7P7R1R8
    </billid>
    <billname>
     한국진도개 보호·육성법 전부개정법률안
    </billname>
    <billno>
     2002355
    </billno>
    <committeename>
     농림축산식품해양수산위원회
    </committeename>
    <proposedt>
     2016-09-20
    </proposedt>
    <proposer>
     정병국의원 등 10인
    </proposer>
    <proposerkind>
     의원
    </proposerkind>
    <submitdt>
     2016-09-21
    </submitdt>
   </item>
   <item>
    <billid>
     PRC_P1D6G0A9C2P0B1E7H5L6S5F2S1S9M8
    </billid>
    <billname>
     교원의 지위 향상 및 교육활동 보호를 위한 특별법 일부개정법률안
    </billname>
    <billno>
     2002354
    </billno>
    <committeename>
     교육위원회
    </committeename>
    <proposedt>
     2016-09-20
    </proposedt>
    <proposer>
     노웅래의원 등 10인
    </proposer>
    <proposerkind>
     의원
    </proposerkind>
    <submitdt>
     2016-09-21
    </submitdt>
   </item>
   <item>
    <billid>
     PRC_M1N6Q0S9D2A0G1V7C2B4C4L9N6P6N1
    </billid>
    <billname>
     국회에서의 증언·감정 등에 관한 법률 일부개정법률안
    </billname>
    <billno>
     2002353
    </billno>
    <committeename>
     국회운영위원회
    </committeename>
    <proposedt>
     2016-09-20
    </proposedt>
    <proposer>
     박용진의원 등 10인
    </proposer>
    <proposerkind>
     의원
    </proposerkind>
    <submitdt>
     2016-09-21
    </submitdt>
   </item>
   <item>
    <billid>
     PRC_G1I6Z0B9F2A0M1V6S3J1Y0U0R0O0P9
    </billid>
    <billname>
     초·중등교육법 일부개정법률안
    </billname>
    <billno>
     2002350
    </billno>
    <committeename>
     교육위원회
    </committeename>
    <proposedt>
     2016-09-20
    </proposedt>
    <proposer>
     장정숙의원 등 10인
    </proposer>
    <proposerkind>
     의원
    </proposerkind>
    <submitdt>
     2016-09-21
    </submitdt>
   </item>
   <item>
    <billid>
     PRC_C1Q6K0F9N2F0R1S5M2A2D3J6O7I3S9
    </billid>
    <billname>
     법인세법 일부개정법률안
    </billname>
    <billno>
     2002345
    </billno>
    <committeename>
     기획재정위원회
    </committeename>
    <proposedt>
     2016-09-20
    </proposedt>
    <proposer>
     배덕광의원 등 10인
    </proposer>
    <proposerkind>
     의원
    </proposerkind>
    <submitdt>
     2016-09-21
    </submitdt>
   </item>
   <item>
    <billid>
     PRC_L1I6U0Q9B2H0A1B5S2V1D1I7X4D0T7
    </billid>
    <billname>
     소득세법 일부개정법률안
    </billname>
    <billno>
     2002344
    </billno>
    <committeename>
     기획재정위원회
    </committeename>
    <proposedt>
     2016-09-20
    </proposedt>
    <proposer>
     배덕광의원 등 10인
    </proposer>
    <proposerkind>
     의원
    </proposerkind>
    <submitdt>
     2016-09-21
    </submitdt>
   </item>
   <item>
    <billid>
     PRC_G1S6K0E9O2E0R1O4R5L4F5P4D6E1O8
    </billid>
    <billname>
     형법 일부개정법률안
    </billname>
    <billno>
     2002343
    </billno>
    <committeename>
     법제사법위원회
    </committeename>
    <proposedt>
     2016-09-20
    </proposedt>
    <proposer>
     금태섭의원 등 11인
    </proposer>
    <proposerkind>
     의원
    </proposerkind>
    <submitdt>
     2016-09-21
    </submitdt>
   </item>
   <item>
    <billid>
     PRC_L1P6N0Q9V2Q0Y1C4M5H2R3I3C4C8H3
    </billid>
    <billname>
     보험업법 일부개정법률안
    </billname>
    <billno>
     2002342
    </billno>
    <committeename>
     정무위원회
    </committeename>
    <proposedt>
     2016-09-20
    </proposedt>
    <proposer>
     김정재의원 등 11인
    </proposer>
    <proposerkind>
     의원
    </proposerkind>
    <submitdt>
     2016-09-21
    </submitdt>
   </item>
   <item>
    <billid>
     PRC_W1M6R0L9S2J0D1P4G4I4A0D2A8T0U3
    </billid>
    <billname>
     근로기준법 일부개정법률안
    </billname>
    <billno>
     2002339
    </billno>
    <committeename>
     환경노동위원회
    </committeename>
    <proposedt>
     2016-09-20
    </proposedt>
    <proposer>
     이정미의원 등 10인
    </proposer>
    <proposerkind>
     의원
    </proposerkind>
    <submitdt>
     2016-09-21
    </submitdt>
   </item>
   <item>
    <billid>
     PRC_E1O6N0N9M2G0T1W4W3W9K4W6O6O3E6
    </billid>
    <billname>
     고용정책 기본법 일부개정법률안
    </billname>
    <billno>
     2002338
    </billno>
    <committeename>
     환경노동위원회
    </committeename>
    <proposedt>
     2016-09-20
    </proposedt>
    <proposer>
     이정미의원 등 11인
    </proposer>
    <proposerkind>
     의원
    </proposerkind>
    <submitdt>
     2016-09-21
    </submitdt>
   </item>
   <item>
    <billid>
     PRC_B1T6H0S9J1E9E1G8R4X7W4I4F1I4H7
    </billid>
    <billname>
     국가보훈 기본법 일부개정법률안
    </billname>
    <billno>
     2002335
    </billno>
    <committeename>
     정무위원회
    </committeename>
    <proposedt>
     2016-09-19
    </proposedt>
    <proposer>
     최경환의원 등 25인
    </proposer>
    <proposerkind>
     의원
    </proposerkind>
    <submitdt>
     2016-09-20
    </submitdt>
   </item>
   <item>
    <billid>
     PRC_O1K6L0P9H1B9P1C8Z0R9O2P0A0P8Z3
    </billid>
    <billname>
     민주시민교육지원법안
    </billname>
    <billno>
     2002333
    </billno>
    <committeename>
     행정안전위원회
    </committeename>
    <proposedt>
     2016-09-19
    </proposedt>
    <proposer>
     남인순의원 등 12인
    </proposer>
    <proposerkind>
     의원
    </proposerkind>
    <submitdt>
     2016-09-20
    </submitdt>
   </item>
   <item>
    <billid>
     PRC_R1B6Y0F9O1E9D1T8C0Q5A1B0Y9Q8W1
    </billid>
    <billname>
     아동복지법 일부개정법률안
    </billname>
    <billno>
     2002332
    </billno>
    <committeename>
     보건복지위원회
    </committeename>
    <proposedt>
     2016-09-19
    </proposedt>
    <proposer>
     김철민의원 등 13인
    </proposer>
    <proposerkind>
     의원
    </proposerkind>
    <submitdt>
     2016-09-20
    </submitdt>
   </item>
   <item>
    <billid>
     PRC_G1Y6X0V9M1J9D1A8N0P1Y2M6U7O6M1
    </billid>
    <billname>
     지방교육재정교부금법 일부개정법률안
    </billname>
    <billno>
     2002331
    </billno>
    <committeename>
     교육위원회
    </committeename>
    <proposedt>
     2016-09-19
    </proposedt>
    <proposer>
     이석현의원 등 11인
    </proposer>
    <proposerkind>
     의원
    </proposerkind>
    <submitdt>
     2016-09-20
    </submitdt>
   </item>
   <item>
    <billid>
     PRC_E1V6V0D9D1U9Q1W8N0S0N2T3L7D5E0
    </billid>
    <billname>
     장애인·노인·임산부 등의 편의증진 보장에 관한 법률 일부개정법률안
    </billname>
    <billno>
     2002330
    </billno>
    <committeename>
     보건복지위원회
    </committeename>
    <proposedt>
     2016-09-19
    </proposedt>
    <proposer>
     이석현의원 등 11인
    </proposer>
    <proposerkind>
     의원
    </proposerkind>
    <submitdt>
     2016-09-20
    </submitdt>
   </item>
   <item>
    <billid>
     PRC_T1E6I0I9J1Q9Y1V7Q4B9D5G6P9S3H3
    </billid>
    <billname>
     도로교통법 일부개정법률안
    </billname>
    <billno>
     2002329
    </billno>
    <committeename>
     행정안전위원회
    </committeename>
    <proposedt>
     2016-09-19
    </proposedt>
    <proposer>
     이석현의원 등 11인
    </proposer>
    <proposerkind>
     의원
    </proposerkind>
    <submitdt>
     2016-09-20
    </submitdt>
   </item>
   <item>
    <billid>
     PRC_I1G6T0B9D1D9K1W6O3L7W2X1K8I8A1
    </billid>
    <billname>
     농업기계화 촉진법 일부개정법률안
    </billname>
    <billno>
     2002328
    </billno>
    <committeename>
     농림축산식품해양수산위원회
    </committeename>
    <proposedt>
     2016-09-19
    </proposedt>
    <proposer>
     이개호의원 등 10인
    </proposer>
    <proposerkind>
     의원
    </proposerkind>
    <submitdt>
     2016-09-20
    </submitdt>
   </item>
   <item>
    <billid>
     PRC_Q1L6H0J9G1B9C1Y6G3J1I1A0L8H7W3
    </billid>
    <billname>
     유료도로법 일부개정법률안
    </billname>
    <billno>
     2002327
    </billno>
    <committeename>
     국토교통위원회
    </committeename>
    <proposedt>
     2016-09-19
    </proposedt>
    <proposer>
     이석현의원 등 11인
    </proposer>
    <proposerkind>
     의원
    </proposerkind>
    <submitdt>
     2016-09-20
    </submitdt>
   </item>
   <item>
    <billid>
     PRC_A1L6W0Q9X1M9C1I6H2U5O3W5N5X5Y0
    </billid>
    <billname>
     건축법 일부개정법률안
    </billname>
    <billno>
     2002326
    </billno>
    <committeename>
     국토교통위원회
    </committeename>
    <proposedt>
     2016-09-19
    </proposedt>
    <proposer>
     전해철의원 등 12인
    </proposer>
    <proposerkind>
     의원
    </proposerkind>
    <submitdt>
     2016-09-20
    </submitdt>
   </item>
   <item>
    <billid>
     PRC_S1F6E0K9X1P9L1E5B3C9R4T4C0S5I4
    </billid>
    <billname>
     근로자퇴직급여 보장법 일부개정법률안
    </billname>
    <billno>
     2002324
    </billno>
    <committeename>
     환경노동위원회
    </committeename>
    <proposedt>
     2016-09-19
    </proposedt>
    <proposer>
     한정애의원 등 12인
    </proposer>
    <proposerkind>
     의원
    </proposerkind>
    <submitdt>
     2016-09-20
    </submitdt>
   </item>
   <item>
    <billid>
     PRC_Y1L6P0C9O1Y9X1R5V2H6U5S9A8Y3B5
    </billid>
    <billname>
     범죄피해자보호기금법 일부개정법률안
    </billname>
    <billno>
     2002323
    </billno>
    <committeename>
     법제사법위원회
    </committeename>
    <proposedt>
     2016-09-19
    </proposedt>
    <proposer>
     정갑윤의원 등 12인
    </proposer>
    <proposerkind>
     의원
    </proposerkind>
    <submitdt>
     2016-09-20
    </submitdt>
   </item>
   <item>
    <billid>
     PRC_Y1K6K0W9D1T9I1D5M2I5I2X0R4K7Z3
    </billid>
    <billname>
     범죄피해자 보호법 일부개정법률안
    </billname>
    <billno>
     2002322
    </billno>
    <committeename>
     법제사법위원회
    </committeename>
    <proposedt>
     2016-09-19
    </proposedt>
    <proposer>
     정갑윤의원 등 11인
    </proposer>
    <proposerkind>
     의원
    </proposerkind>
    <submitdt>
     2016-09-20
    </submitdt>
   </item>
   <item>
    <billid>
     PRC_A1O6L0S9I1L9A1Y4U5K9E4S0D3I1P9
    </billid>
    <billname>
     법인세법 일부개정법률안
    </billname>
    <billno>
     2002321
    </billno>
    <committeename>
     기획재정위원회
    </committeename>
    <proposedt>
     2016-09-19
    </proposedt>
    <proposer>
     윤호중의원 등 13인
    </proposer>
    <proposerkind>
     의원
    </proposerkind>
    <submitdt>
     2016-09-20
    </submitdt>
   </item>
   <item>
    <billid>
     PRC_V1P6Z0X9K1U9D1Z0S4U4H3F6K0J8Q1
    </billid>
    <billname>
     공직선거법 일부개정법률안
    </billname>
    <billno>
     2002315
    </billno>
    <committeename>
     정치개혁 특별위원회
    </committeename>
    <proposedt>
     2016-09-19
    </proposedt>
    <proposer>
     박주민의원 등 10인
    </proposer>
    <proposerkind>
     의원
    </proposerkind>
    <submitdt>
     2018-10-19
    </submitdt>
   </item>
   <item>
    <billid>
     PRC_V1F6S0N9E1P9Q1H0H0P5L0D0T2C2N9
    </billid>
    <billname>
     화학무기·생물무기의 금지와 특정화학물질·생물작용제 등의 제조·수출입 규제 등에 관한 법률 일부개정법률안
    </billname>
    <billno>
     2002314
    </billno>
    <committeename>
     산업통상자원중소벤처기업위원회
    </committeename>
    <proposedt>
     2016-09-19
    </proposedt>
    <proposer>
     박재호의원 등 44인
    </proposer>
    <proposerkind>
     의원
    </proposerkind>
    <submitdt>
     2016-09-20
    </submitdt>
   </item>
   <item>
    <billid>
     PRC_K1W6U0L9R1M9E0C9M5R2Y0U6O3I8O2
    </billid>
    <billname>
     감염병의 예방 및 관리에 관한 법률 일부개정법률안
    </billname>
    <billno>
     2002313
    </billno>
    <committeename>
     보건복지위원회
    </committeename>
    <proposedt>
     2016-09-19
    </proposedt>
    <proposer>
     박재호의원 등 44인
    </proposer>
    <proposerkind>
     의원
    </proposerkind>
    <submitdt>
     2016-09-20
    </submitdt>
   </item>
   <item>
    <billid>
     PRC_I1L6Z0U9Z1F3X1J8G0B3T4X3A4R1D9
    </billid>
    <billname>
     일제하 일본군위안부 피해자에 대한 생활안정지원 및 기념사업 등에 관한 법률 일부개정법률안
    </billname>
    <billno>
     2002312
    </billno>
    <committeename>
     여성가족위원회
    </committeename>
    <proposedt>
     2016-09-13
    </proposedt>
    <proposer>
     황주홍의원 등 13인
    </proposer>
    <proposerkind>
     의원
    </proposerkind>
    <submitdt>
     2016-09-19
    </submitdt>
   </item>
   <item>
    <billid>
     PRC_G1L6T0O9I1B3D1P7X1I5V1M4P0V9Z6
    </billid>
    <billname>
     북한이탈주민의 보호 및 정착지원에 관한 법률 일부개정법률안
    </billname>
    <billno>
     2002309
    </billno>
    <committeename>
     외교통일위원회
    </committeename>
    <proposedt>
     2016-09-13
    </proposedt>
    <proposer>
     나경원의원 등 10인
    </proposer>
    <proposerkind>
     의원
    </proposerkind>
    <submitdt>
     2016-09-19
    </submitdt>
   </item>
   <item>
    <billid>
     PRC_H1Y6D0X9Q1G3J1X6H4K3I2B9Q3I6Z3
    </billid>
    <billname>
     인신보호법 일부개정법률안
    </billname>
    <billno>
     2002308
    </billno>
    <committeename>
     법제사법위원회
    </committeename>
    <proposedt>
     2016-09-13
    </proposedt>
    <proposer>
     나경원의원 등 10인
    </proposer>
    <proposerkind>
     의원
    </proposerkind>
    <submitdt>
     2016-09-19
    </submitdt>
   </item>
   <item>
    <billid>
     PRC_Z1U6P0W9D1P3C1T5K3N9C4I3X5B4H2
    </billid>
    <billname>
     변호사법 일부개정법률안
    </billname>
    <billno>
     2002307
    </billno>
    <committeename>
     법제사법위원회
    </committeename>
    <proposedt>
     2016-09-13
    </proposedt>
    <proposer>
     권성동의원 등 10인
    </proposer>
    <proposerkind>
     의원
    </proposerkind>
    <submitdt>
     2016-09-19
    </submitdt>
   </item>
   <item>
    <billid>
     PRC_B1P6M0D9G1I3Z1P4Y4Y8E0G4U8I9S8
    </billid>
    <billname>
     국민체육진흥법 일부개정법률안
    </billname>
    <billno>
     2002306
    </billno>
    <committeename>
     문화체육관광위원회
    </committeename>
    <proposedt>
     2016-09-13
    </proposedt>
    <proposer>
     염동열의원 등 10인
    </proposer>
    <proposerkind>
     의원
    </proposerkind>
    <submitdt>
     2016-09-19
    </submitdt>
   </item>
   <item>
    <billid>
     PRC_D1P6V0K9J1V3X1K1W3V2Z5A5P3J6J4
    </billid>
    <billname>
     집단에너지사업법 일부개정법률안
    </billname>
    <billno>
     2002305
    </billno>
    <committeename>
     산업통상자원중소벤처기업위원회
    </committeename>
    <proposedt>
     2016-09-13
    </proposedt>
    <proposer>
     박정의원 등 12인
    </proposer>
    <proposerkind>
     의원
    </proposerkind>
    <submitdt>
     2016-09-19
    </submitdt>
   </item>
   <item>
    <billid>
     PRC_F1R6E0W9B1M3O1T1L3A0O0M0A0F2Z3
    </billid>
    <billname>
     전기사업법 일부개정법률안
    </billname>
    <billno>
     2002304
    </billno>
    <committeename>
     산업통상자원중소벤처기업위원회
    </committeename>
    <proposedt>
     2016-09-13
    </proposedt>
    <proposer>
     박정의원 등 12인
    </proposer>
    <proposerkind>
     의원
    </proposerkind>
    <submitdt>
     2016-09-19
    </submitdt>
   </item>
   <item>
    <billid>
     PRC_T1Q6H0Q9O1L3L1W1J2M3X4E4G6W0B4
    </billid>
    <billname>
     국민기초생활 보장법 일부개정법률안
    </billname>
    <billno>
     2002303
    </billno>
    <committeename>
     보건복지위원회
    </committeename>
    <proposedt>
     2016-09-13
    </proposedt>
    <proposer>
     지상욱의원 등 31인
    </proposer>
    <proposerkind>
     의원
    </proposerkind>
    <submitdt>
     2016-09-19
    </submitdt>
   </item>
   <item>
    <billid>
     PRC_U1M6F0J9Y1Q3L1S0W3X6T0F1R0Q5Q4
    </billid>
    <billname>
     공휴일에 관한 법률안
    </billname>
    <billno>
     2002300
    </billno>
    <committeename>
     행정안전위원회
    </committeename>
    <proposedt>
     2016-09-13
    </proposedt>
    <proposer>
     심재권의원 등 17인
    </proposer>
    <proposerkind>
     의원
    </proposerkind>
    <submitdt>
     2016-09-19
    </submitdt>
   </item>
   <item>
    <billid>
     PRC_Z1M6F0P9E1U3M0Q9Y4Y1L0R1O7Q6D7
    </billid>
    <billname>
     소득세법 일부개정법률안
    </billname>
    <billno>
     2002296
    </billno>
    <committeename>
     기획재정위원회
    </committeename>
    <proposedt>
     2016-09-12
    </proposedt>
    <proposer>
     박광온의원 등 10인
    </proposer>
    <proposerkind>
     의원
    </proposerkind>
    <submitdt>
     2016-09-13
    </submitdt>
   </item>
   <item>
    <billid>
     PRC_M1E6E0W9X1M2T1E7P5N1J2Y0U4V1R8
    </billid>
    <billname>
     공공기관의 운영에 관한 법률 일부개정법률안
    </billname>
    <billno>
     2002295
    </billno>
    <committeename>
     기획재정위원회
    </committeename>
    <proposedt>
     2016-09-12
    </proposedt>
    <proposer>
     천정배의원 등 12인
    </proposer>
    <proposerkind>
     의원
    </proposerkind>
    <submitdt>
     2016-09-13
    </submitdt>
   </item>
   <item>
    <billid>
     PRC_P1A6N0U9Y1Q2Q1O7C4C6E0P4C4G7I0
    </billid>
    <billname>
     공적자금관리 특별법 일부개정법률안
    </billname>
    <billno>
     2002294
    </billno>
    <committeename>
     정무위원회
    </committeename>
    <proposedt>
     2016-09-12
    </proposedt>
    <proposer>
     제윤경의원 등 25인
    </proposer>
    <proposerkind>
     의원
    </proposerkind>
    <submitdt>
     2016-09-13
    </submitdt>
   </item>
   <item>
    <billid>
     PRC_H1W6Y0C9S1O2W1C7R2K2I3N5V7F9S6
    </billid>
    <billname>
     국가재정법 일부개정법률안
    </billname>
    <billno>
     2002292
    </billno>
    <committeename>
     기획재정위원회
    </committeename>
    <proposedt>
     2016-09-12
    </proposedt>
    <proposer>
     노웅래의원 등 10인
    </proposer>
    <proposerkind>
     의원
    </proposerkind>
    <submitdt>
     2016-09-13
    </submitdt>
   </item>
   <item>
    <billid>
     PRC_D1N6G0Q9I1V2V1W7D2H0H0X7C4K4M3
    </billid>
    <billname>
     국민연금법 일부개정법률안
    </billname>
    <billno>
     2002291
    </billno>
    <committeename>
     보건복지위원회
    </committeename>
    <proposedt>
     2016-09-12
    </proposedt>
    <proposer>
     노웅래의원 등 10인
    </proposer>
    <proposerkind>
     의원
    </proposerkind>
    <submitdt>
     2016-09-13
    </submitdt>
   </item>
   <item>
    <billid>
     PRC_C1F6Y0R9M1Q2V1C6F5N3N5P0A3K1T7
    </billid>
    <billname>
     저작권법 일부개정법률안
    </billname>
    <billno>
     2002290
    </billno>
    <committeename>
     문화체육관광위원회
    </committeename>
    <proposedt>
     2016-09-12
    </proposedt>
    <proposer>
     최도자의원 등 16인
    </proposer>
    <proposerkind>
     의원
    </proposerkind>
    <submitdt>
     2016-09-13
    </submitdt>
   </item>
   <item>
    <billid>
     PRC_Y1S6T0G9T1P2S1I6L4O8R2M4N6L4A7
    </billid>
    <billname>
     주택임대차보호법 일부개정법률안
    </billname>
    <billno>
     2002288
    </billno>
    <committeename>
     법제사법위원회
    </committeename>
    <proposedt>
     2016-09-12
    </proposedt>
    <proposer>
     김성찬의원 등 10인
    </proposer>
    <proposerkind>
     의원
    </proposerkind>
    <submitdt>
     2016-09-13
    </submitdt>
   </item>
   <item>
    <billid>
     PRC_M1X6C0I9Z1R2J1N6E4O6C2K7Z5Q5X7
    </billid>
    <billname>
     위법한 재정행위에 대한 국민소송법안
    </billname>
    <billno>
     2002287
    </billno>
    <committeename>
     법제사법위원회
    </committeename>
    <proposedt>
     2016-09-12
    </proposedt>
    <proposer>
     천정배의원 등 14인
    </proposer>
    <proposerkind>
     의원
    </proposerkind>
    <submitdt>
     2016-09-13
    </submitdt>
   </item>
   <item>
    <billid>
     PRC_L1R6Y0Q9N1N2C1J5F5D8D3O7Q3Q7O4
    </billid>
    <billname>
     민법 일부개정법률안
    </billname>
    <billno>
     2002283
    </billno>
    <committeename>
     법제사법위원회
    </committeename>
    <proposedt>
     2016-09-12
    </proposedt>
    <proposer>
     민병두의원 등 11인
    </proposer>
    <proposerkind>
     의원
    </proposerkind>
    <submitdt>
     2016-09-13
    </submitdt>
   </item>
   <item>
    <billid>
     PRC_P1W6M0S9Z1Z2V1C5P5P7R4O3Y8T1E6
    </billid>
    <billname>
     부가가치세법 일부개정법률안
    </billname>
    <billno>
     2002282
    </billno>
    <committeename>
     기획재정위원회
    </committeename>
    <proposedt>
     2016-09-12
    </proposedt>
    <proposer>
     이명수의원 등 11인
    </proposer>
    <proposerkind>
     의원
    </proposerkind>
    <submitdt>
     2016-09-13
    </submitdt>
   </item>
   <item>
    <billid>
     PRC_B1S6H0M9M1C2H1I5V5C4F1R4P1X6U1
    </billid>
    <billname>
     전기사업법 일부개정법률안
    </billname>
    <billno>
     2002281
    </billno>
    <committeename>
     산업통상자원중소벤처기업위원회
    </committeename>
    <proposedt>
     2016-09-12
    </proposedt>
    <proposer>
     이명수의원 등 10인
    </proposer>
    <proposerkind>
     의원
    </proposerkind>
    <submitdt>
     2016-09-13
    </submitdt>
   </item>
   <item>
    <billid>
     PRC_L1E6O0Z9F1M2P1G5K4N7F2G7E0X4K5
    </billid>
    <billname>
     도로법 일부개정법률안
    </billname>
    <billno>
     2002280
    </billno>
    <committeename>
     국토교통위원회
    </committeename>
    <proposedt>
     2016-09-12
    </proposedt>
    <proposer>
     주광덕의원 등 10인
    </proposer>
    <proposerkind>
     의원
    </proposerkind>
    <submitdt>
     2016-09-13
    </submitdt>
   </item>
   <item>
    <billid>
     PRC_M1O6L0K9Q1N2S1W4D2G3I4F2W3K2K4
    </billid>
    <billname>
     조세특례제한법 일부개정법률안
    </billname>
    <billno>
     2002276
    </billno>
    <committeename>
     기획재정위원회
    </committeename>
    <proposedt>
     2016-09-12
    </proposedt>
    <proposer>
     추경호의원 등 14인
    </proposer>
    <proposerkind>
     의원
    </proposerkind>
    <submitdt>
     2016-09-13
    </submitdt>
   </item>
   <item>
    <billid>
     PRC_T1S6G0D9P1C2X1R3D3Y8K1M0T0A9O5
    </billid>
    <billname>
     상속세 및 증여세법 일부개정법률안
    </billname>
    <billno>
     2002274
    </billno>
    <committeename>
     기획재정위원회
    </committeename>
    <proposedt>
     2016-09-12
    </proposedt>
    <proposer>
     추경호의원 등 14인
    </proposer>
    <proposerkind>
     의원
    </proposerkind>
    <submitdt>
     2016-09-13
    </submitdt>
   </item>
   <item>
    <billid>
     PRC_P1W6A0S9N1E2U1U1X0B2P5O0K1U3A7
    </billid>
    <billname>
     지방세법 일부개정법률안
    </billname>
    <billno>
     2002272
    </billno>
    <committeename>
     행정안전위원회
    </committeename>
    <proposedt>
     2016-09-12
    </proposedt>
    <proposer>
     장제원의원 등 10인
    </proposer>
    <proposerkind>
     의원
    </proposerkind>
    <submitdt>
     2016-09-13
    </submitdt>
   </item>
   <item>
    <billid>
     PRC_A1J6S0P9B1Q2Z1X0A4R5X0W8G8D2A8
    </billid>
    <billname>
     어선안전조업법안
    </billname>
    <billno>
     2002271
    </billno>
    <committeename>
     농림축산식품해양수산위원회
    </committeename>
    <proposedt>
     2016-09-12
    </proposedt>
    <proposer>
     유기준의원 등 20인
    </proposer>
    <proposerkind>
     의원
    </proposerkind>
    <submitdt>
     2016-09-13
    </submitdt>
   </item>
   <item>
    <billid>
     PRC_U1F6L0Q9W0V9D1E7K1B7W0X3V4J5E2
    </billid>
    <billname>
     북한 제5차 핵실험 규탄 결의안
    </billname>
    <billno>
     2002270
    </billno>
    <committeename>
     국방위원회
    </committeename>
    <proposedt>
     2016-09-12
    </proposedt>
    <proposer>
     국방위원장
    </proposer>
    <proposerkind>
     위원장
    </proposerkind>
   </item>
   <item>
    <billid>
     PRC_S1X6J0M9C1Z2D0O9R3A1H1A5H9D7D1
    </billid>
    <billname>
     지방세기본법 일부개정법률안
    </billname>
    <billno>
     2002268
    </billno>
    <committeename>
     행정안전위원회
    </committeename>
    <proposedt>
     2016-09-12
    </proposedt>
    <proposer>
     장제원의원 등 10인
    </proposer>
    <proposerkind>
     의원
    </proposerkind>
    <submitdt>
     2016-09-13
    </submitdt>
   </item>
   <item>
    <billid>
     PRC_P1V6R0Y9A1L2R0C9X2D5O4V1T9Q7M3
    </billid>
    <billname>
     국경일 및 공휴일에 관한 법률안
    </billname>
    <billno>
     2002267
    </billno>
    <committeename>
     행정안전위원회
    </committeename>
    <proposedt>
     2016-09-12
    </proposedt>
    <proposer>
     장제원의원 등 10인
    </proposer>
    <proposerkind>
     의원
    </proposerkind>
    <submitdt>
     2016-09-13
    </submitdt>
   </item>
   <item>
    <billid>
     ARC_J1X6S0E9H0X9J1U7E5W8R0V2R5D2T1
    </billid>
    <billname>
     제대군인지원에 관한 법률 일부개정법률안
    </billname>
    <billno>
     2002266
    </billno>
    <committeename>
     정무위원회
    </committeename>
    <proposedt>
     2016-09-09
    </proposedt>
    <proposer>
     정부
    </proposer>
    <proposerkind>
     정부
    </proposerkind>
    <submitdt>
     2016-09-12
    </submitdt>
   </item>
   <item>
    <billid>
     PRC_S1S6A0F9S0T9C1E7F5X7Q4C4G9O2Z6
    </billid>
    <billname>
     국유재산법 일부개정법률안
    </billname>
    <billno>
     2002265
    </billno>
    <committeename>
     기획재정위원회
    </committeename>
    <proposedt>
     2016-09-09
    </proposedt>
    <proposer>
     주광덕의원 등 10인
    </proposer>
    <proposerkind>
     의원
    </proposerkind>
    <submitdt>
     2016-09-12
    </submitdt>
   </item>
   <item>
    <billid>
     PRC_U1T6R0K9V0O9E1S7W2S6D3E6T9G9Q4
    </billid>
    <billname>
     채무자 회생 및 파산에 관한 법률 일부개정법률안
    </billname>
    <billno>
     2002259
    </billno>
    <committeename>
     법제사법위원회
    </committeename>
    <proposedt>
     2016-09-09
    </proposedt>
    <proposer>
     노회찬의원 등 10인
    </proposer>
    <proposerkind>
     의원
    </proposerkind>
    <submitdt>
     2016-09-12
    </submitdt>
   </item>
   <item>
    <billid>
     PRC_P1U6H0C9Y0L9F1P6M3I6R5E6V9N2Y1
    </billid>
    <billname>
     정보통신망 이용촉진 및 정보보호 등에 관한 법률 일부개정법률안
    </billname>
    <billno>
     2002255
    </billno>
    <committeename>
     과학기술정보방송통신위원회
    </committeename>
    <proposedt>
     2016-09-09
    </proposedt>
    <proposer>
     이원욱의원 등 11인
    </proposer>
    <proposerkind>
     의원
    </proposerkind>
    <submitdt>
     2016-09-12
    </submitdt>
   </item>
   <item>
    <billid>
     PRC_F1L6U0A9T0A9S1R6K3Q4R0N0Z4Q4O4
    </billid>
    <billname>
     과학기술기본법 일부개정법률안
    </billname>
    <billno>
     2002254
    </billno>
    <committeename>
     과학기술정보방송통신위원회
    </committeename>
    <proposedt>
     2016-09-09
    </proposedt>
    <proposer>
     신용현의원 등 12인
    </proposer>
    <proposerkind>
     의원
    </proposerkind>
    <submitdt>
     2016-09-12
    </submitdt>
   </item>
   <item>
    <billid>
     PRC_X1E6J0F9F0R9K1D6E2E9K3V9A8Z8B0
    </billid>
    <billname>
     방송법 일부개정법률안
    </billname>
    <billno>
     2002253
    </billno>
    <committeename>
     과학기술정보방송통신위원회
    </committeename>
    <proposedt>
     2016-09-09
    </proposedt>
    <proposer>
     박홍근의원 등 10인
    </proposer>
    <proposerkind>
     의원
    </proposerkind>
    <submitdt>
     2016-09-12
    </submitdt>
   </item>
   <item>
    <billid>
     PRC_D1M6A0H9K0E9V1B6P2E6F3J6A8G0G9
    </billid>
    <billname>
     자동차관리법 일부개정법률안
    </billname>
    <billno>
     2002252
    </billno>
    <committeename>
     국토교통위원회
    </committeename>
    <proposedt>
     2016-09-09
    </proposedt>
    <proposer>
     박완수의원 등 10인
    </proposer>
    <proposerkind>
     의원
    </proposerkind>
    <submitdt>
     2016-09-12
    </submitdt>
   </item>
   <item>
    <billid>
     PRC_C1F6H0K9P0T9J1X6N2Z5A0O9F4A0I8
    </billid>
    <billname>
     독점규제 및 공정거래에 관한 법률 일부개정법률안
    </billname>
    <billno>
     2002251
    </billno>
    <committeename>
     정무위원회
    </committeename>
    <proposedt>
     2016-09-09
    </proposedt>
    <proposer>
     이원욱의원 등 11인
    </proposer>
    <proposerkind>
     의원
    </proposerkind>
    <submitdt>
     2016-09-12
    </submitdt>
   </item>
   <item>
    <billid>
     PRC_Z1S6J0P9S0G9V1G6J2M4A4U8U7O8C0
    </billid>
    <billname>
     국가공무원법 일부개정법률안
    </billname>
    <billno>
     2002250
    </billno>
    <committeename>
     행정안전위원회
    </committeename>
    <proposedt>
     2016-09-09
    </proposedt>
    <proposer>
     경대수의원 등 12인
    </proposer>
    <proposerkind>
     의원
    </proposerkind>
    <submitdt>
     2016-09-12
    </submitdt>
   </item>
   <item>
    <billid>
     PRC_G1Q6U0Z9N0A9H1R6Y2O0D2F4Z0Y2G1
    </billid>
    <billname>
     향토예비군 설치법 일부개정법률안
    </billname>
    <billno>
     2002247
    </billno>
    <committeename>
     국방위원회
    </committeename>
    <proposedt>
     2016-09-09
    </proposedt>
    <proposer>
     박병석의원 등 19인
    </proposer>
    <proposerkind>
     의원
    </proposerkind>
    <submitdt>
     2016-09-12
    </submitdt>
   </item>
   <item>
    <billid>
     PRC_K1F6P0J9A0B9O1Y5A4S9K5M6B0Q7Y5
    </billid>
    <billname>
     연구실 안전환경 조성에 관한 법률 일부개정법률안
    </billname>
    <billno>
     2002245
    </billno>
    <committeename>
     과학기술정보방송통신위원회
    </committeename>
    <proposedt>
     2016-09-09
    </proposedt>
    <proposer>
     신용현의원 등 12인
    </proposer>
    <proposerkind>
     의원
    </proposerkind>
    <submitdt>
     2016-09-12
    </submitdt>
   </item>
   <item>
    <billid>
     PRC_M1L6M0H9Q0J9V1G5I4U0Y2E7H3T7S4
    </billid>
    <billname>
     농림수산식품투자조합 결성 및 운용에 관한 법률 일부개정법률안
    </billname>
    <billno>
     2002243
    </billno>
    <committeename>
     농림축산식품해양수산위원회
    </committeename>
    <proposedt>
     2016-09-09
    </proposedt>
    <proposer>
     경대수의원 등 10인
    </proposer>
    <proposerkind>
     의원
    </proposerkind>
    <submitdt>
     2016-09-12
    </submitdt>
   </item>
   <item>
    <billid>
     PRC_U1D6A0M9K0E9N1E5S2E9Z2Z3D3U6V0
    </billid>
    <billname>
     지방공무원법 일부개정법률안
    </billname>
    <billno>
     2002241
    </billno>
    <committeename>
     행정안전위원회
    </committeename>
    <proposedt>
     2016-09-09
    </proposedt>
    <proposer>
     경대수의원 등 12인
    </proposer>
    <proposerkind>
     의원
    </proposerkind>
    <submitdt>
     2016-09-12
    </submitdt>
   </item>
   <item>
    <billid>
     PRC_Y1S6Z0W9S0X9N1A5H2L8U3G9R6Q1D7
    </billid>
    <billname>
     고용보험 및 산업재해보상보험의 보험료징수 등에 관한 법률 일부개정법률안
    </billname>
    <billno>
     2002240
    </billno>
    <committeename>
     환경노동위원회
    </committeename>
    <proposedt>
     2016-09-09
    </proposedt>
    <proposer>
     신용현의원 등 12인
    </proposer>
    <proposerkind>
     의원
    </proposerkind>
    <submitdt>
     2016-09-12
    </submitdt>
   </item>
   <item>
    <billid>
     PRC_A1D6V0Q9I0U9A1H5T2K7H1Y0L0S7V9
    </billid>
    <billname>
     산업재해보상보험법 일부개정법률안
    </billname>
    <billno>
     2002239
    </billno>
    <committeename>
     환경노동위원회
    </committeename>
    <proposedt>
     2016-09-09
    </proposedt>
    <proposer>
     신용현의원 등 12인
    </proposer>
    <proposerkind>
     의원
    </proposerkind>
    <submitdt>
     2016-09-12
    </submitdt>
   </item>
   <item>
    <billid>
     PRC_F1M6Y0X9X0Z9B1T5N2W3N1M1B6H1J1
    </billid>
    <billname>
     국경일에 관한 법률 일부개정법률안
    </billname>
    <billno>
     2002238
    </billno>
    <committeename>
     행정안전위원회
    </committeename>
    <proposedt>
     2016-09-09
    </proposedt>
    <proposer>
     백재현의원 등 11인
    </proposer>
    <proposerkind>
     의원
    </proposerkind>
    <submitdt>
     2016-09-12
    </submitdt>
   </item>
   <item>
    <billid>
     PRC_Y1Y6D0F9M0S9Q1L5U0W3Y0A1C5D6Z3
    </billid>
    <billname>
     수산업·어촌 발전 기본법 일부개정법률안
    </billname>
    <billno>
     2002237
    </billno>
    <committeename>
     농림축산식품해양수산위원회
    </committeename>
    <proposedt>
     2016-09-09
    </proposedt>
    <proposer>
     김종회의원 등 13인
    </proposer>
    <proposerkind>
     의원
    </proposerkind>
    <submitdt>
     2016-09-12
    </submitdt>
   </item>
   <item>
    <billid>
     PRC_T1P6K0J9B0B9Z1K4F4K9W3A4G2H9D1
    </billid>
    <billname>
     사회보장기본법 일부개정법률안
    </billname>
    <billno>
     2002235
    </billno>
    <committeename>
     보건복지위원회
    </committeename>
    <proposedt>
     2016-09-09
    </proposedt>
    <proposer>
     오신환의원 등 10인
    </proposer>
    <proposerkind>
     의원
    </proposerkind>
    <submitdt>
     2016-09-12
    </submitdt>
   </item>
   <item>
    <billid>
     PRC_N1Z6C0D9R0Y9P1Q4H3K4J4R3Y9B6M7
    </billid>
    <billname>
     배타적 경제수역에서의 외국인어업 등에 대한 주권적 권리의 행사에 관한 법률 일부개정법률안
    </billname>
    <billno>
     2002234
    </billno>
    <committeename>
     농림축산식품해양수산위원회
    </committeename>
    <proposedt>
     2016-09-09
    </proposedt>
    <proposer>
     김종회의원 등 13인
    </proposer>
    <proposerkind>
     의원
    </proposerkind>
    <submitdt>
     2016-09-12
    </submitdt>
   </item>
   <item>
    <billid>
     PRC_G1U6U0Y9Q0P9U1G3Y5S7W5S0D5L6G1
    </billid>
    <billname>
     전기통신사업법 일부개정법률안
    </billname>
    <billno>
     2002232
    </billno>
    <committeename>
     과학기술정보방송통신위원회
    </committeename>
    <proposedt>
     2016-09-09
    </proposedt>
    <proposer>
     주승용의원 등 11인
    </proposer>
    <proposerkind>
     의원
    </proposerkind>
    <submitdt>
     2016-09-12
    </submitdt>
   </item>
   <item>
    <billid>
     PRC_G1C6G0J9T0J9Z1A3H3N5R0B8E8A7V8
    </billid>
    <billname>
     의료법 일부개정법률안
    </billname>
    <billno>
     2002231
    </billno>
    <committeename>
     보건복지위원회
    </committeename>
    <proposedt>
     2016-09-09
    </proposedt>
    <proposer>
     김종회의원 등 15인
    </proposer>
    <proposerkind>
     의원
    </proposerkind>
    <submitdt>
     2016-09-12
    </submitdt>
   </item>
   <item>
    <billid>
     PRC_C1K6J0C9X0L8R1I6L4G8N5G2X9M2A0
    </billid>
    <billname>
     근로기준법 일부개정법률안
    </billname>
    <billno>
     2002229
    </billno>
    <committeename>
     환경노동위원회
    </committeename>
    <proposedt>
     2016-09-08
    </proposedt>
    <proposer>
     정동영의원 등 17인
    </proposer>
    <proposerkind>
     의원
    </proposerkind>
    <submitdt>
     2016-09-09
    </submitdt>
   </item>
   <item>
    <billid>
     PRC_G1M6A0W9W0D8V1D6E1X5T1A5E3I0H0
    </billid>
    <billname>
     군사기지 및 군사시설 주변지역 지원에 관한 법률안
    </billname>
    <billno>
     2002228
    </billno>
    <committeename>
     국방위원회
    </committeename>
    <proposedt>
     2016-09-08
    </proposedt>
    <proposer>
     박정의원 등 20인
    </proposer>
    <proposerkind>
     의원
    </proposerkind>
    <submitdt>
     2016-09-09
    </submitdt>
   </item>
   <item>
    <billid>
     PRC_A1I6V0X9L0I8F1O6A0E9J4P6R5Q0D8
    </billid>
    <billname>
     형사소송법 일부개정법률안
    </billname>
    <billno>
     2002227
    </billno>
    <committeename>
     법제사법위원회
    </committeename>
    <proposedt>
     2016-09-08
    </proposedt>
    <proposer>
     황주홍의원 등 10인
    </proposer>
    <proposerkind>
     의원
    </proposerkind>
    <submitdt>
     2016-09-09
    </submitdt>
   </item>
   <item>
    <billid>
     PRC_K1I6G0X9K0Q8W1Z5H3E0E2G1B2L0F7
    </billid>
    <billname>
     사회보장기본법 일부개정법률안
    </billname>
    <billno>
     2002223
    </billno>
    <committeename>
     보건복지위원회
    </committeename>
    <proposedt>
     2016-09-08
    </proposedt>
    <proposer>
     박인숙의원 등 10인
    </proposer>
    <proposerkind>
     의원
    </proposerkind>
    <submitdt>
     2016-09-09
    </submitdt>
   </item>
   <item>
    <billid>
     PRC_K1F6M0E9K0I8P1O4Z1X7K4I9P9F0X2
    </billid>
    <billname>
     국토의 계획 및 이용에 관한 법률 일부개정법률안
    </billname>
    <billno>
     2002221
    </billno>
    <committeename>
     국토교통위원회
    </committeename>
    <proposedt>
     2016-09-08
    </proposedt>
    <proposer>
     임종성의원 등 20인
    </proposer>
    <proposerkind>
     의원
    </proposerkind>
    <submitdt>
     2016-09-09
    </submitdt>
   </item>
   <item>
    <billid>
     PRC_D1P6J0X9T0T8I1L4V0J9A5F1A7T0W8
    </billid>
    <billname>
     개별소비세법 일부개정법률안
    </billname>
    <billno>
     2002220
    </billno>
    <committeename>
     기획재정위원회
    </committeename>
    <proposedt>
     2016-09-08
    </proposedt>
    <proposer>
     강효상의원 등 21인
    </proposer>
    <proposerkind>
     의원
    </proposerkind>
    <submitdt>
     2016-09-09
    </submitdt>
   </item>
   <item>
    <billid>
     PRC_C1M6C0T9Z0J8Y1Z3E5H5B2H6R2O2X6
    </billid>
    <billname>
     파견근로자보호 등에 관한 법률 일부개정법률안
    </billname>
    <billno>
     2002219
    </billno>
    <committeename>
     환경노동위원회
    </committeename>
    <proposedt>
     2016-09-08
    </proposedt>
    <proposer>
     신경민의원 등 19인
    </proposer>
    <proposerkind>
     의원
    </proposerkind>
    <submitdt>
     2016-09-09
    </submitdt>
   </item>
   <item>
    <billid>
     PRC_T1A6I0W9Z0D8Z1O3F5F3Y2W7T4Z2S1
    </billid>
    <billname>
     근로기준법 일부개정법률안
    </billname>
    <billno>
     2002218
    </billno>
    <committeename>
     환경노동위원회
    </committeename>
    <proposedt>
     2016-09-08
    </proposedt>
    <proposer>
     신경민의원 등 20인
    </proposer>
    <proposerkind>
     의원
    </proposerkind>
    <submitdt>
     2016-09-09
    </submitdt>
   </item>
   <item>
    <billid>
     PRC_V1F6H0Q9X0B8U1Z1E2U5X4Y6E4G0A2
    </billid>
    <billname>
     공인탐정법안
    </billname>
    <billno>
     2002216
    </billno>
    <committeename>
     행정안전위원회
    </committeename>
    <proposedt>
     2016-09-08
    </proposedt>
    <proposer>
     윤재옥의원 등 12인
    </proposer>
    <proposerkind>
     의원
    </proposerkind>
    <submitdt>
     2016-09-09
    </submitdt>
   </item>
   <item>
    <billid>
     PRC_H1K6F0B9Q0K8U0N9D4N9X1P9D0N4A8
    </billid>
    <billname>
     군형법 일부개정법률안
    </billname>
    <billno>
     2002215
    </billno>
    <committeename>
     법제사법위원회
    </committeename>
    <proposedt>
     2016-09-08
    </proposedt>
    <proposer>
     신상진의원 등 10인
    </proposer>
    <proposerkind>
     의원
    </proposerkind>
    <submitdt>
     2016-09-09
    </submitdt>
   </item>
   <item>
    <billid>
     PRC_C1R6V0O9I0Z7G1P6I5Q4V5U0Q4W7F7
    </billid>
    <billname>
     정보통신망 이용촉진 및 정보보호 등에 관한 법률 일부개정법률안
    </billname>
    <billno>
     2002213
    </billno>
    <committeename>
     과학기술정보방송통신위원회
    </committeename>
    <proposedt>
     2016-09-07
    </proposedt>
    <proposer>
     유승희의원 등 10인
    </proposer>
    <proposerkind>
     의원
    </proposerkind>
    <submitdt>
     2016-09-08
    </submitdt>
   </item>
   <item>
    <billid>
     PRC_B1I6T0U9W0W7D1L5B5D9M5J5H4X2B8
    </billid>
    <billname>
     환경오염피해 배상책임 및 구제에 관한 법률 일부개정법률안
    </billname>
    <billno>
     2002211
    </billno>
    <committeename>
     환경노동위원회
    </committeename>
    <proposedt>
     2016-09-07
    </proposedt>
    <proposer>
     어기구의원 등 11인
    </proposer>
    <proposerkind>
     의원
    </proposerkind>
    <submitdt>
     2016-09-08
    </submitdt>
   </item>
   <item>
    <billid>
     PRC_F1X6F0U9J0F7N1E5V5W0N1I9W5A7S0
    </billid>
    <billname>
     국회의원(한선교) 징계안
    </billname>
    <billno>
     2002210
    </billno>
    <committeename>
     윤리특별위원회
    </committeename>
    <proposedt>
     2016-09-07
    </proposedt>
    <proposer>
     우상호의원 등 3인 외 159인
    </proposer>
    <proposerkind>
     의원
    </proposerkind>
    <submitdt>
     2018-09-27
    </submitdt>
   </item>
   <item>
    <billid>
     PRC_T1H6T0U9E0Y7Q1V5W4F9H4F3O7J5S5
    </billid>
    <billname>
     국제경기대회 지원법 일부개정법률안
    </billname>
    <billno>
     2002209
    </billno>
    <committeename>
     문화체육관광위원회
    </committeename>
    <proposedt>
     2016-09-07
    </proposedt>
    <proposer>
     최명길의원 등 14인
    </proposer>
    <proposerkind>
     의원
    </proposerkind>
    <submitdt>
     2016-09-08
    </submitdt>
   </item>
   <item>
    <billid>
     PRC_U1V6H0V9O0L7T1W5K2L1H0H3B5M4T6
    </billid>
    <billname>
     고용보험법 일부개정법률안
    </billname>
    <billno>
     2002208
    </billno>
    <committeename>
     환경노동위원회
    </committeename>
    <proposedt>
     2016-09-07
    </proposedt>
    <proposer>
     이정미의원 등 10인
    </proposer>
    <proposerkind>
     의원
    </proposerkind>
    <submitdt>
     2016-09-08
    </submitdt>
   </item>
  </items>
  <numOfRows>
   100
  </numOfRows>
  <pageNo>
   121
  </pageNo>
  <totalCount>
   13476
  </totalCount>
 </body>
</response>